termoto/__init__.py
termoto/cli.py
termoto/todoro.py
termato-1.0.dist-info/LICENSE
termato-1.0.dist-info/METADATA
termato-1.0.dist-info/WHEEL
termato-1.0.dist-info/entry_points.txt
termato-1.0.dist-info/top_level.txt
termato-1.0.dist-info/RECORD
