Metadata-Version: 2.1
Name: termato
Version: 1.0
Summary: A simple CLI Pomodoro timer.
Home-page: https://github.com/1darshanpatil/termato
Author: Darshan P.
Author-email: drshnp@outlook.com
License: MIT
Project-URL: Documentation, https://github.com/1darshanpatil/termoto#readme
Project-URL: Source, https://github.com/1darshanpatil/termoto
Project-URL: Tracker, https://github.com/1darshanpatil/termoto/issues
Keywords: pomodoro,cli,time,productivity
Classifier: Development Status :: 4 - Beta
Classifier: Environment :: Console
Classifier: Intended Audience :: End Users/Desktop
Classifier: Topic :: Utilities
Classifier: Topic :: Office/Business :: Scheduling
Classifier: Programming Language :: Python :: 3
Classifier: License :: OSI Approved :: MIT License
Classifier: Operating System :: OS Independent
Requires-Python: >=3.6
License-File: LICENSE
Requires-Dist: colorama
